AUTHORS.rst
CONTRIBUTING.rst
HISTORY.rst
LICENSE
MANIFEST.in
README.md
classifiers
requirements.txt
setup.cfg
setup.py
django_sessioninfo.egg-info/PKG-INFO
django_sessioninfo.egg-info/SOURCES.txt
django_sessioninfo.egg-info/dependency_links.txt
django_sessioninfo.egg-info/not-zip-safe
django_sessioninfo.egg-info/requires.txt
django_sessioninfo.egg-info/top_level.txt
sessioninfo/__init__.py
sessioninfo/admin.py
sessioninfo/apps.py
sessioninfo/models.py
sessioninfo/urls.py
sessioninfo/utils.py
sessioninfo/views.py
sessioninfo/management/__init__.py
sessioninfo/management/commands/__init__.py
sessioninfo/management/commands/kill_sessions.py
sessioninfo/static/css/sessioninfo.css
sessioninfo/static/img/.gitignore
sessioninfo/static/js/sessioninfo.js
sessioninfo/templates/sessioninfo/base.html
sessioninfo/templatetags/__init__.py
sessioninfo/templatetags/_tags.py
sessioninfo/tests/__init__.py
sessioninfo/tests/manage_settings.py
sessioninfo/tests/south_settings.py
sessioninfo/tests/test_sessioninfo.py
sessioninfo/tests/test_settings.py
sessioninfo/tests/urls.py
sessioninfo/tests/test_app/__init__.py
sessioninfo/tests/test_app/models.py
sessioninfo/tests/test_app/views.py
sessioninfo/tests/test_app/templates/400.html
sessioninfo/tests/test_app/templates/500.html