Metadata-Version: 1.1
Name: django-sessioninfo
Version: 0.0.5
Summary: Your project description goes here
Home-page: https://github.com/arteria/django-sessioninfo
Author: arteria GmbH
Author-email: admin@arteria.ch
License: BSD
Keywords: django-sessioninfo
Platform: UNKNOWN
Classifier: Development Status :: 2 - Pre-Alpha
Classifier: Framework :: Django
Classifier: Intended Audience :: Developers
Classifier: License :: OSI Approved :: BSD License
Classifier: Natural Language :: English
Classifier: Programming Language :: Python :: 2
Classifier: Programming Language :: Python :: 3
